nonebot_plugin_course_schedule/__init__.py
nonebot_plugin_course_schedule/commands/bind_group.py
nonebot_plugin_course_schedule/commands/bind_schedule.py
nonebot_plugin_course_schedule/commands/group_schedule.py
nonebot_plugin_course_schedule/commands/show_today.py
nonebot_plugin_course_schedule/commands/weekly_ranking.py
nonebot_plugin_course_schedule/config.py
nonebot_plugin_course_schedule/resources/MapleMono-NF-CN-Medium.ttf
nonebot_plugin_course_schedule/utils/constants.py
nonebot_plugin_course_schedule/utils/data_manager.py
nonebot_plugin_course_schedule/utils/ics_parser.py
nonebot_plugin_course_schedule/utils/image_generator.py
nonebot_plugin_course_schedule-1.0.5.dist-info/METADATA
nonebot_plugin_course_schedule-1.0.5.dist-info/WHEEL
nonebot_plugin_course_schedule-1.0.5.dist-info/licenses/LICENSE
nonebot_plugin_course_schedule-1.0.5.dist-info/RECORD
