Metadata-Version: 2.4
Name: nonebot-plugin-course-schedule
Version: 1.0.5
Summary: 电子课程表
License-Expression: AGPL-3.0
License-File: LICENSE
Keywords: 课程,course
Author: Polaris_Light
Author-email: 995905922@qq.com
Requires-Python: >=3.10
Classifier: Programming Language :: Python :: 3
Classifier: Programming Language :: Python :: 3.10
Classifier: Programming Language :: Python :: 3.11
Classifier: Programming Language :: Python :: 3.12
Classifier: Programming Language :: Python :: 3.13
Classifier: Programming Language :: Python :: 3.14
Requires-Dist: Pillow (>=11.0.0)
Requires-Dist: aiohttp (>=3.8.0)
Requires-Dist: icalendar (>=6.3.1)
Requires-Dist: nonebot-adapter-onebot (>=2.0.0b1)
Requires-Dist: nonebot-plugin-apscheduler (>=0.4.0)
Requires-Dist: nonebot-plugin-localstore (>=0.7.4)
Requires-Dist: nonebot2 (>=2.2.1)
Requires-Dist: pydantic (>=1.10)
Requires-Dist: python-dateutil (>=2.8.0)
Project-URL: Homepage, https://github.com/GLDYM/nonebot-plugin-course-schedule
